geohash/__init__.py
test/__init__.py
test/test_decode.py
test/test_encode.py
test/test_geohash.py
geohash_python-0.1.0.dist-info/LICENSE
geohash_python-0.1.0.dist-info/METADATA
geohash_python-0.1.0.dist-info/WHEEL
geohash_python-0.1.0.dist-info/top_level.txt
geohash_python-0.1.0.dist-info/RECORD
