Metadata-Version: 2.1
Name: geohash-python
Version: 0.1.0
Summary: A Python implementation of the Geohash algorithm compatible with python-geohash
Home-page: https://github.com/alitrack/geohash-python
Author: Steven Lee
Author-email: alitrack.com@gmail.com
Project-URL: Bug Tracker, https://github.com/alitrack/geohash-python/issues
Project-URL: Documentation, https://github.com/alitrack/geohash-python
Project-URL: Source Code, https://github.com/alitrack/geohash-python
Keywords: geohash,geo,spatial,location,uint64,gis
Classifier: Development Status :: 4 - Beta
Classifier: Intended Audience :: Developers
Classifier: License :: OSI Approved :: MIT License
Classifier: Operating System :: OS Independent
Classifier: Programming Language :: Python :: 3
Classifier: Programming Language :: Python :: 3.6
Classifier: Programming Language :: Python :: 3.7
Classifier: Programming Language :: Python :: 3.8
Classifier: Programming Language :: Python :: 3.9
Classifier: Programming Language :: Python :: 3.10
Classifier: Topic :: Scientific/Engineering :: GIS
Classifier: Topic :: Software Development :: Libraries :: Python Modules
Requires-Python: >=3.6
License-File: LICENSE
